{
  "summary": {
    "generatedon": "2026-04-23T16:14:48Z",
    "parser": "MultiReportParser (2x OpenCoverParser)",
    "assemblies": 11,
    "classes": 231,
    "files": 214,
    "coveredlines": 1663,
    "uncoveredlines": 19225,
    "coverablelines": 20888,
    "totallines": 43542,
    "linecoverage": 7.9,
    "coveredbranches": 0,
    "totalbranches": 0,
    "coveredmethods": 179,
    "totalmethods": 2349,
    "methodcoverage": 7.6
 },
  "coverage": {
    "assemblies": [
      { "name": "Assembly-CSharp", "classes": 41, "coverage": 0, "coveredlines": 0, "coverablelines": 2411, "totallines": 5244, "branchcoverage": null, "coveredbranches": 0, "totalbranches": 0, "methodcoverage": 0, "coveredmethods": 0, "totalmethods": 189, "classesinassembly": [
        { "name": "ChangeInput", "coverage": 0, "coveredlines": 0, "coverablelines": 26, "totallines": 43, "branchcoverage": null, "coveredbranches": 0, "totalbranches": 0, "methodcoverage": 0, "coveredmethods": 0, "totalmethods": 2 },
        { "name": "ChatController", "coverage": 0, "coveredlines": 0, "coverablelines": 19, "totallines": 51, "branchcoverage": null, "coveredbranches": 0, "totalbranches": 0, "methodcoverage": 0, "coveredmethods": 0, "totalmethods": 3 },
        { "name": "ClickButton", "coverage": 0, "coveredlines": 0, "coverablelines": 9, "totallines": 26, "branchcoverage": null, "coveredbranches": 0, "totalbranches": 0, "methodcoverage": 0, "coveredmethods": 0, "totalmethods": 2 },
        { "name": "Dialog", "coverage": 0, "coveredlines": 0, "coverablelines": 33, "totallines": 52, "branchcoverage": null, "coveredbranches": 0, "totalbranches": 0, "methodcoverage": 0, "coveredmethods": 0, "totalmethods": 5 },
        { "name": "DialogCall", "coverage": 0, "coveredlines": 0, "coverablelines": 7, "totallines": 21, "branchcoverage": null, "coveredbranches": 0, "totalbranches": 0, "methodcoverage": 0, "coveredmethods": 0, "totalmethods": 3 },
        { "name": "DialogInit", "coverage": 0, "coveredlines": 0, "coverablelines": 8, "totallines": 20, "branchcoverage": null, "coveredbranches": 0, "totalbranches": 0, "methodcoverage": 0, "coveredmethods": 0, "totalmethods": 2 },
        { "name": "DigitalRuby.RainMaker.RainCollision", "coverage": 0, "coveredlines": 0, "coverablelines": 36, "totallines": 64, "branchcoverage": null, "coveredbranches": 0, "totalbranches": 0, "methodcoverage": 0, "coveredmethods": 0, "totalmethods": 6 },
        { "name": "DigitalRuby.RainMaker.RainScript", "coverage": 0, "coveredlines": 0, "coverablelines": 44, "totallines": 72, "branchcoverage": null, "coveredbranches": 0, "totalbranches": 0, "methodcoverage": 0, "coveredmethods": 0, "totalmethods": 4 },
        { "name": "DropdownSample", "coverage": 0, "coveredlines": 0, "coverablelines": 6, "totallines": 19, "branchcoverage": null, "coveredbranches": 0, "totalbranches": 0, "methodcoverage": 0, "coveredmethods": 0, "totalmethods": 2 },
        { "name": "EnvMapAnimator", "coverage": 0, "coveredlines": 0, "coverablelines": 12, "totallines": 35, "branchcoverage": null, "coveredbranches": 0, "totalbranches": 0, "methodcoverage": 0, "coveredmethods": 0, "totalmethods": 2 },
        { "name": "TMPro.Examples.Benchmark01", "coverage": 0, "coveredlines": 0, "coverablelines": 44, "totallines": 128, "branchcoverage": null, "coveredbranches": 0, "totalbranches": 0, "methodcoverage": 0, "coveredmethods": 0, "totalmethods": 2 },
        { "name": "TMPro.Examples.Benchmark01_UGUI", "coverage": 0, "coveredlines": 0, "coverablelines": 39, "totallines": 135, "branchcoverage": null, "coveredbranches": 0, "totalbranches": 0, "methodcoverage": 0, "coveredmethods": 0, "totalmethods": 2 },
        { "name": "TMPro.Examples.Benchmark02", "coverage": 0, "coveredlines": 0, "coverablelines": 54, "totallines": 97, "branchcoverage": null, "coveredbranches": 0, "totalbranches": 0, "methodcoverage": 0, "coveredmethods": 0, "totalmethods": 2 },
        { "name": "TMPro.Examples.Benchmark03", "coverage": 0, "coveredlines": 0, "coverablelines": 46, "totallines": 92, "branchcoverage": null, "coveredbranches": 0, "totalbranches": 0, "methodcoverage": 0, "coveredmethods": 0, "totalmethods": 3 },
        { "name": "TMPro.Examples.Benchmark04", "coverage": 0, "coveredlines": 0, "coverablelines": 30, "totallines": 85, "branchcoverage": null, "coveredbranches": 0, "totalbranches": 0, "methodcoverage": 0, "coveredmethods": 0, "totalmethods": 2 },
        { "name": "TMPro.Examples.CameraController", "coverage": 0, "coveredlines": 0, "coverablelines": 168, "totallines": 292, "branchcoverage": null, "coveredbranches": 0, "totalbranches": 0, "methodcoverage": 0, "coveredmethods": 0, "totalmethods": 5 },
        { "name": "TMPro.Examples.ObjectSpin", "coverage": 0, "coveredlines": 0, "coverablelines": 26, "totallines": 67, "branchcoverage": null, "coveredbranches": 0, "totalbranches": 0, "methodcoverage": 0, "coveredmethods": 0, "totalmethods": 3 },
        { "name": "TMPro.Examples.ShaderPropAnimator", "coverage": 0, "coveredlines": 0, "coverablelines": 16, "totallines": 51, "branchcoverage": null, "coveredbranches": 0, "totalbranches": 0, "methodcoverage": 0, "coveredmethods": 0, "totalmethods": 3 },
        { "name": "TMPro.Examples.SimpleScript", "coverage": 0, "coveredlines": 0, "coverablelines": 11, "totallines": 58, "branchcoverage": null, "coveredbranches": 0, "totalbranches": 0, "methodcoverage": 0, "coveredmethods": 0, "totalmethods": 2 },
        { "name": "TMPro.Examples.SkewTextExample", "coverage": 0, "coveredlines": 0, "coverablelines": 78, "totallines": 158, "branchcoverage": null, "coveredbranches": 0, "totalbranches": 0, "methodcoverage": 0, "coveredmethods": 0, "totalmethods": 5 },
        { "name": "TMPro.Examples.TeleType", "coverage": 0, "coveredlines": 0, "coverablelines": 28, "totallines": 83, "branchcoverage": null, "coveredbranches": 0, "totalbranches": 0, "methodcoverage": 0, "coveredmethods": 0, "totalmethods": 3 },
        { "name": "TMPro.Examples.TextConsoleSimulator", "coverage": 0, "coveredlines": 0, "coverablelines": 60, "totallines": 121, "branchcoverage": null, "coveredbranches": 0, "totalbranches": 0, "methodcoverage": 0, "coveredmethods": 0, "totalmethods": 7 },
        { "name": "TMPro.Examples.TextMeshProFloatingText", "coverage": 0, "coveredlines": 0, "coverablelines": 108, "totallines": 223, "branchcoverage": null, "coveredbranches": 0, "totalbranches": 0, "methodcoverage": 0, "coveredmethods": 0, "totalmethods": 6 },
        { "name": "TMPro.Examples.TextMeshSpawner", "coverage": 0, "coveredlines": 0, "coverablelines": 33, "totallines": 79, "branchcoverage": null, "coveredbranches": 0, "totalbranches": 0, "methodcoverage": 0, "coveredmethods": 0, "totalmethods": 3 },
        { "name": "TMPro.Examples.TMP_ExampleScript_01", "coverage": 0, "coveredlines": 0, "coverablelines": 18, "totallines": 64, "branchcoverage": null, "coveredbranches": 0, "totalbranches": 0, "methodcoverage": 0, "coveredmethods": 0, "totalmethods": 2 },
        { "name": "TMPro.Examples.TMP_FrameRateCounter", "coverage": 0, "coveredlines": 0, "coverablelines": 65, "totallines": 134, "branchcoverage": null, "coveredbranches": 0, "totalbranches": 0, "methodcoverage": 0, "coveredmethods": 0, "totalmethods": 5 },
        { "name": "TMPro.Examples.TMP_TextEventCheck", "coverage": 0, "coveredlines": 0, "coverablelines": 40, "totallines": 73, "branchcoverage": null, "coveredbranches": 0, "totalbranches": 0, "methodcoverage": 0, "coveredmethods": 0, "totalmethods": 7 },
        { "name": "TMPro.Examples.TMP_TextInfoDebugTool", "coverage": 0, "coveredlines": 0, "coverablelines": 344, "totallines": 652, "branchcoverage": null, "coveredbranches": 0, "totalbranches": 0, "methodcoverage": 0, "coveredmethods": 0, "totalmethods": 14 },
        { "name": "TMPro.Examples.TMP_TextSelector_A", "coverage": 0, "coveredlines": 0, "coverablelines": 73, "totallines": 157, "branchcoverage": null, "coveredbranches": 0, "totalbranches": 0, "methodcoverage": 0, "coveredmethods": 0, "totalmethods": 5 },
        { "name": "TMPro.Examples.TMP_TextSelector_B", "coverage": 0, "coveredlines": 0, "coverablelines": 198, "totallines": 547, "branchcoverage": null, "coveredbranches": 0, "totalbranches": 0, "methodcoverage": 0, "coveredmethods": 0, "totalmethods": 11 },
        { "name": "TMPro.Examples.TMP_UiFrameRateCounter", "coverage": 0, "coveredlines": 0, "coverablelines": 71, "totallines": 125, "branchcoverage": null, "coveredbranches": 0, "totalbranches": 0, "methodcoverage": 0, "coveredmethods": 0, "totalmethods": 5 },
        { "name": "TMPro.Examples.TMPro_InstructionOverlay", "coverage": 0, "coveredlines": 0, "coverablelines": 33, "totallines": 84, "branchcoverage": null, "coveredbranches": 0, "totalbranches": 0, "methodcoverage": 0, "coveredmethods": 0, "totalmethods": 3 },
        { "name": "TMPro.Examples.VertexColorCycler", "coverage": 0, "coveredlines": 0, "coverablelines": 33, "totallines": 84, "branchcoverage": null, "coveredbranches": 0, "totalbranches": 0, "methodcoverage": 0, "coveredmethods": 0, "totalmethods": 3 },
        { "name": "TMPro.Examples.VertexJitter", "coverage": 0, "coveredlines": 0, "coverablelines": 80, "totallines": 175, "branchcoverage": null, "coveredbranches": 0, "totalbranches": 0, "methodcoverage": 0, "coveredmethods": 0, "totalmethods": 7 },
        { "name": "TMPro.Examples.VertexShakeA", "coverage": 0, "coveredlines": 0, "coverablelines": 80, "totallines": 161, "branchcoverage": null, "coveredbranches": 0, "totalbranches": 0, "methodcoverage": 0, "coveredmethods": 0, "totalmethods": 7 },
        { "name": "TMPro.Examples.VertexShakeB", "coverage": 0, "coveredlines": 0, "coverablelines": 93, "totallines": 185, "branchcoverage": null, "coveredbranches": 0, "totalbranches": 0, "methodcoverage": 0, "coveredmethods": 0, "totalmethods": 7 },
        { "name": "TMPro.Examples.VertexZoom", "coverage": 0, "coveredlines": 0, "coverablelines": 91, "totallines": 192, "branchcoverage": null, "coveredbranches": 0, "totalbranches": 0, "methodcoverage": 0, "coveredmethods": 0, "totalmethods": 7 },
        { "name": "TMPro.Examples.WarpTextExample", "coverage": 0, "coveredlines": 0, "coverablelines": 70, "totallines": 144, "branchcoverage": null, "coveredbranches": 0, "totalbranches": 0, "methodcoverage": 0, "coveredmethods": 0, "totalmethods": 5 },
        { "name": "TMPro.TMP_DigitValidator", "coverage": 0, "coveredlines": 0, "coverablelines": 8, "totallines": 27, "branchcoverage": null, "coveredbranches": 0, "totalbranches": 0, "methodcoverage": 0, "coveredmethods": 0, "totalmethods": 1 },
        { "name": "TMPro.TMP_PhoneNumberValidator", "coverage": 0, "coveredlines": 0, "coverablelines": 66, "totallines": 105, "branchcoverage": null, "coveredbranches": 0, "totalbranches": 0, "methodcoverage": 0, "coveredmethods": 0, "totalmethods": 1 },
        { "name": "TMPro.TMP_TextEventHandler", "coverage": 0, "coveredlines": 0, "coverablelines": 107, "totallines": 263, "branchcoverage": null, "coveredbranches": 0, "totalbranches": 0, "methodcoverage": 0, "coveredmethods": 0, "totalmethods": 20 } ] },
      { "name": "Assembly-CSharp-Editor", "classes": 1, "coverage": 0, "coveredlines": 0, "coverablelines": 32, "totallines": 64, "branchcoverage": null, "coveredbranches": 0, "totalbranches": 0, "methodcoverage": 0, "coveredmethods": 0, "totalmethods": 1, "classesinassembly": [
        { "name": "DigitalRuby.RainMaker.RainMakerEditor", "coverage": 0, "coveredlines": 0, "coverablelines": 32, "totallines": 64, "branchcoverage": null, "coveredbranches": 0, "totalbranches": 0, "methodcoverage": 0, "coveredmethods": 0, "totalmethods": 1 } ] },
      { "name": "Boxophobic.SkyboxCubemapExtended.Editor", "classes": 3, "coverage": 0, "coveredlines": 0, "coverablelines": 94, "totallines": 187, "branchcoverage": null, "coveredbranches": 0, "totalbranches": 0, "methodcoverage": 0, "coveredmethods": 0, "totalmethods": 12, "classesinassembly": [
        { "name": "SkyboxExtendedHub", "coverage": 0, "coveredlines": 0, "coverablelines": 59, "totallines": 108, "branchcoverage": null, "coveredbranches": 0, "totalbranches": 0, "methodcoverage": 0, "coveredmethods": 0, "totalmethods": 5 },
        { "name": "SkyboxExtendedShaderGUI", "coverage": 0, "coveredlines": 0, "coverablelines": 20, "totallines": 42, "branchcoverage": null, "coveredbranches": 0, "totalbranches": 0, "methodcoverage": 0, "coveredmethods": 0, "totalmethods": 2 },
        { "name": "SkyboxExtendedWindows", "coverage": 0, "coveredlines": 0, "coverablelines": 15, "totallines": 37, "branchcoverage": null, "coveredbranches": 0, "totalbranches": 0, "methodcoverage": 0, "coveredmethods": 0, "totalmethods": 5 } ] },
      { "name": "Boxophobic.Utils.Editor", "classes": 37, "coverage": 2.1, "coveredlines": 33, "coverablelines": 1550, "totallines": 2814, "branchcoverage": null, "coveredbranches": 0, "totalbranches": 0, "methodcoverage": 5.8, "coveredmethods": 8, "totalmethods": 136, "classesinassembly": [
        { "name": "Boxophobic.Constants.CONSTANT", "coverage": 0, "coveredlines": 0, "coverablelines": 28, "totallines": 86, "branchcoverage": null, "coveredbranches": 0, "totalbranches": 0, "methodcoverage": 0, "coveredmethods": 0, "totalmethods": 6 },
        { "name": "Boxophobic.StyledGUI.StyledBannerAttributeDrawer", "coverage": 0, "coveredlines": 0, "coverablelines": 8, "totallines": 27, "branchcoverage": null, "coveredbranches": 0, "totalbranches": 0, "methodcoverage": 0, "coveredmethods": 0, "totalmethods": 2 },
        { "name": "Boxophobic.StyledGUI.StyledBannerDrawer", "coverage": 40, "coveredlines": 4, "coverablelines": 10, "totallines": 28, "branchcoverage": null, "coveredbranches": 0, "totalbranches": 0, "methodcoverage": 33.3, "coveredmethods": 1, "totalmethods": 3 },
        { "name": "Boxophobic.StyledGUI.StyledButtonAttributeDrawer", "coverage": 0, "coveredlines": 0, "coverablelines": 12, "totallines": 33, "branchcoverage": null, "coveredbranches": 0, "totalbranches": 0, "methodcoverage": 0, "coveredmethods": 0, "totalmethods": 2 },
        { "name": "Boxophobic.StyledGUI.StyledButtonDrawer", "coverage": 0, "coveredlines": 0, "coverablelines": 45, "totallines": 71, "branchcoverage": null, "coveredbranches": 0, "totalbranches": 0, "methodcoverage": 0, "coveredmethods": 0, "totalmethods": 5 },
        { "name": "Boxophobic.StyledGUI.StyledCategoryAttributeDrawer", "coverage": 0, "coveredlines": 0, "coverablelines": 7, "totallines": 25, "branchcoverage": null, "coveredbranches": 0, "totalbranches": 0, "methodcoverage": 0, "coveredmethods": 0, "totalmethods": 2 },
        { "name": "Boxophobic.StyledGUI.StyledCategoryDrawer", "coverage": 17.8, "coveredlines": 15, "coverablelines": 84, "totallines": 124, "branchcoverage": null, "coveredbranches": 0, "totalbranches": 0, "methodcoverage": 62.5, "coveredmethods": 5, "totalmethods": 8 },
        { "name": "Boxophobic.StyledGUI.StyledDiffusionMaterialDrawer", "coverage": 0, "coveredlines": 0, "coverablelines": 46, "totallines": 93, "branchcoverage": null, "coveredbranches": 0, "totalbranches": 0, "methodcoverage": 0, "coveredmethods": 0, "totalmethods": 3 },
        { "name": "Boxophobic.StyledGUI.StyledEnumAttributeDrawer", "coverage": 0, "coveredlines": 0, "coverablelines": 44, "totallines": 86, "branchcoverage": null, "coveredbranches": 0, "totalbranches": 0, "methodcoverage": 0, "coveredmethods": 0, "totalmethods": 2 },
        { "name": "Boxophobic.StyledGUI.StyledEnumDrawer", "coverage": 0, "coveredlines": 0, "coverablelines": 50, "totallines": 92, "branchcoverage": null, "coveredbranches": 0, "totalbranches": 0, "methodcoverage": 0, "coveredmethods": 0, "totalmethods": 3 },
        { "name": "Boxophobic.StyledGUI.StyledGUI", "coverage": 0, "coveredlines": 0, "coverablelines": 198, "totallines": 331, "branchcoverage": null, "coveredbranches": 0, "totalbranches": 0, "methodcoverage": 0, "coveredmethods": 0, "totalmethods": 12 },
        { "name": "Boxophobic.StyledGUI.StyledIndentAttributeDrawer", "coverage": 0, "coveredlines": 0, "coverablelines": 7, "totallines": 25, "branchcoverage": null, "coveredbranches": 0, "totalbranches": 0, "methodcoverage": 0, "coveredmethods": 0, "totalmethods": 2 },
        { "name": "Boxophobic.StyledGUI.StyledIndentDrawer", "coverage": 0, "coveredlines": 0, "coverablelines": 10, "totallines": 30, "branchcoverage": null, "coveredbranches": 0, "totalbranches": 0, "methodcoverage": 0, "coveredmethods": 0, "totalmethods": 3 },
        { "name": "Boxophobic.StyledGUI.StyledInteractiveAttributeDrawer", "coverage": 0, "coveredlines": 0, "coverablelines": 12, "totallines": 28, "branchcoverage": null, "coveredbranches": 0, "totalbranches": 0, "methodcoverage": 0, "coveredmethods": 0, "totalmethods": 2 },
        { "name": "Boxophobic.StyledGUI.StyledInteractiveDrawer", "coverage": 0, "coveredlines": 0, "coverablelines": 15, "totallines": 33, "branchcoverage": null, "coveredbranches": 0, "totalbranches": 0, "methodcoverage": 0, "coveredmethods": 0, "totalmethods": 3 },
        { "name": "Boxophobic.StyledGUI.StyledLayersAttributeDrawer", "coverage": 0, "coveredlines": 0, "coverablelines": 24, "totallines": 49, "branchcoverage": null, "coveredbranches": 0, "totalbranches": 0, "methodcoverage": 0, "coveredmethods": 0, "totalmethods": 2 },
        { "name": "Boxophobic.StyledGUI.StyledLayersDrawer", "coverage": 0, "coveredlines": 0, "coverablelines": 32, "totallines": 74, "branchcoverage": null, "coveredbranches": 0, "totalbranches": 0, "methodcoverage": 0, "coveredmethods": 0, "totalmethods": 4 },
        { "name": "Boxophobic.StyledGUI.StyledMaskAttributeDrawer", "coverage": 0, "coveredlines": 0, "coverablelines": 37, "totallines": 77, "branchcoverage": null, "coveredbranches": 0, "totalbranches": 0, "methodcoverage": 0, "coveredmethods": 0, "totalmethods": 2 },
        { "name": "Boxophobic.StyledGUI.StyledMaskDrawer", "coverage": 0, "coveredlines": 0, "coverablelines": 42, "totallines": 83, "branchcoverage": null, "coveredbranches": 0, "totalbranches": 0, "methodcoverage": 0, "coveredmethods": 0, "totalmethods": 3 },
        { "name": "Boxophobic.StyledGUI.StyledMessageAttributeDrawer", "coverage": 0, "coveredlines": 0, "coverablelines": 29, "totallines": 52, "branchcoverage": null, "coveredbranches": 0, "totalbranches": 0, "methodcoverage": 0, "coveredmethods": 0, "totalmethods": 2 },
        { "name": "Boxophobic.StyledGUI.StyledMessageDrawer", "coverage": 14, "coveredlines": 9, "coverablelines": 64, "totallines": 100, "branchcoverage": null, "coveredbranches": 0, "totalbranches": 0, "methodcoverage": 20, "coveredmethods": 1, "totalmethods": 5 },
        { "name": "Boxophobic.StyledGUI.StyledMonoBehaviourEditor", "coverage": 0, "coveredlines": 0, "coverablelines": 7, "totallines": 20, "branchcoverage": null, "coveredbranches": 0, "totalbranches": 0, "methodcoverage": 0, "coveredmethods": 0, "totalmethods": 1 },
        { "name": "Boxophobic.StyledGUI.StyledRangeOptionsAttributeDrawer", "coverage": 0, "coveredlines": 0, "coverablelines": 38, "totallines": 71, "branchcoverage": null, "coveredbranches": 0, "totalbranches": 0, "methodcoverage": 0, "coveredmethods": 0, "totalmethods": 2 },
        { "name": "Boxophobic.StyledGUI.StyledScriptableObjectEditor", "coverage": 0, "coveredlines": 0, "coverablelines": 7, "totallines": 20, "branchcoverage": null, "coveredbranches": 0, "totalbranches": 0, "methodcoverage": 0, "coveredmethods": 0, "totalmethods": 1 },
        { "name": "Boxophobic.StyledGUI.StyledSpaceAttributeDrawer", "coverage": 0, "coveredlines": 0, "coverablelines": 7, "totallines": 25, "branchcoverage": null, "coveredbranches": 0, "totalbranches": 0, "methodcoverage": 0, "coveredmethods": 0, "totalmethods": 2 },
        { "name": "Boxophobic.StyledGUI.StyledSpaceDrawer", "coverage": 0, "coveredlines": 0, "coverablelines": 35, "totallines": 60, "branchcoverage": null, "coveredbranches": 0, "totalbranches": 0, "methodcoverage": 0, "coveredmethods": 0, "totalmethods": 4 },
        { "name": "Boxophobic.StyledGUI.StyledTextAttributeDrawer", "coverage": 0, "coveredlines": 0, "coverablelines": 11, "totallines": 38, "branchcoverage": null, "coveredbranches": 0, "totalbranches": 0, "methodcoverage": 0, "coveredmethods": 0, "totalmethods": 2 },
        { "name": "Boxophobic.StyledGUI.StyledTextDrawer", "coverage": 0, "coveredlines": 0, "coverablelines": 64, "totallines": 97, "branchcoverage": null, "coveredbranches": 0, "totalbranches": 0, "methodcoverage": 0, "coveredmethods": 0, "totalmethods": 5 },
        { "name": "Boxophobic.StyledGUI.StyledTextureDrawer", "coverage": 0, "coveredlines": 0, "coverablelines": 41, "totallines": 70, "branchcoverage": null, "coveredbranches": 0, "totalbranches": 0, "methodcoverage": 0, "coveredmethods": 0, "totalmethods": 5 },
        { "name": "Boxophobic.StyledGUI.StyledTexturePreviewAttributeDrawer", "coverage": 0, "coveredlines": 0, "coverablelines": 56, "totallines": 100, "branchcoverage": null, "coveredbranches": 0, "totalbranches": 0, "methodcoverage": 0, "coveredmethods": 0, "totalmethods": 3 },
        { "name": "Boxophobic.StyledGUI.StyledTextureSingleLineDrawer", "coverage": 27.7, "coveredlines": 5, "coverablelines": 18, "totallines": 39, "branchcoverage": null, "coveredbranches": 0, "totalbranches": 0, "methodcoverage": 25, "coveredmethods": 1, "totalmethods": 4 },
        { "name": "Boxophobic.StyledGUI.StyledToggleDrawer", "coverage": 0, "coveredlines": 0, "coverablelines": 57, "totallines": 94, "branchcoverage": null, "coveredbranches": 0, "totalbranches": 0, "methodcoverage": 0, "coveredmethods": 0, "totalmethods": 4 },
        { "name": "Boxophobic.StyledGUI.StyledVectorDrawer", "coverage": 0, "coveredlines": 0, "coverablelines": 29, "totallines": 50, "branchcoverage": null, "coveredbranches": 0, "totalbranches": 0, "methodcoverage": 0, "coveredmethods": 0, "totalmethods": 4 },
        { "name": "Boxophobic.Utils.SettingsUtils", "coverage": 0, "coveredlines": 0, "coverablelines": 69, "totallines": 142, "branchcoverage": null, "coveredbranches": 0, "totalbranches": 0, "methodcoverage": 0, "coveredmethods": 0, "totalmethods": 8 },
        { "name": "StyledEmissiveIntensityDrawer", "coverage": 0, "coveredlines": 0, "coverablelines": 71, "totallines": 114, "branchcoverage": null, "coveredbranches": 0, "totalbranches": 0, "methodcoverage": 0, "coveredmethods": 0, "totalmethods": 7 },
        { "name": "StyledOptionsSliderDrawer", "coverage": 0, "coveredlines": 0, "coverablelines": 137, "totallines": 184, "branchcoverage": null, "coveredbranches": 0, "totalbranches": 0, "methodcoverage": 0, "coveredmethods": 0, "totalmethods": 4 },
        { "name": "StyledRemapSliderDrawer", "coverage": 0, "coveredlines": 0, "coverablelines": 99, "totallines": 143, "branchcoverage": null, "coveredbranches": 0, "totalbranches": 0, "methodcoverage": 0, "coveredmethods": 0, "totalmethods": 4 } ] },
      { "name": "Boxophobic.Utils.Scripts", "classes": 15, "coverage": 0, "coveredlines": 0, "coverablelines": 194, "totallines": 509, "branchcoverage": null, "coveredbranches": 0, "totalbranches": 0, "methodcoverage": 0, "coveredmethods": 0, "totalmethods": 31, "classesinassembly": [
        { "name": "Boxophobic.StyledGUI.StyledBanner", "coverage": 0, "coveredlines": 0, "coverablelines": 42, "totallines": 63, "branchcoverage": null, "coveredbranches": 0, "totalbranches": 0, "methodcoverage": 0, "coveredmethods": 0, "totalmethods": 6 },
        { "name": "Boxophobic.StyledGUI.StyledButton", "coverage": 0, "coveredlines": 0, "coverablelines": 15, "totallines": 28, "branchcoverage": null, "coveredbranches": 0, "totalbranches": 0, "methodcoverage": 0, "coveredmethods": 0, "totalmethods": 2 },
        { "name": "Boxophobic.StyledGUI.StyledCategory", "coverage": 0, "coveredlines": 0, "coverablelines": 28, "totallines": 45, "branchcoverage": null, "coveredbranches": 0, "totalbranches": 0, "methodcoverage": 0, "coveredmethods": 0, "totalmethods": 4 },
        { "name": "Boxophobic.StyledGUI.StyledEnum", "coverage": 0, "coveredlines": 0, "coverablelines": 20, "totallines": 34, "branchcoverage": null, "coveredbranches": 0, "totalbranches": 0, "methodcoverage": 0, "coveredmethods": 0, "totalmethods": 2 },
        { "name": "Boxophobic.StyledGUI.StyledIndent", "coverage": 0, "coveredlines": 0, "coverablelines": 4, "totallines": 17, "branchcoverage": null, "coveredbranches": 0, "totalbranches": 0, "methodcoverage": 0, "coveredmethods": 0, "totalmethods": 1 },
        { "name": "Boxophobic.StyledGUI.StyledInteractive", "coverage": 0, "coveredlines": 0, "coverablelines": 3, "totallines": 15, "branchcoverage": null, "coveredbranches": 0, "totalbranches": 0, "methodcoverage": 0, "coveredmethods": 0, "totalmethods": 1 },
        { "name": "Boxophobic.StyledGUI.StyledLayers", "coverage": 0, "coveredlines": 0, "coverablelines": 8, "totallines": 20, "branchcoverage": null, "coveredbranches": 0, "totalbranches": 0, "methodcoverage": 0, "coveredmethods": 0, "totalmethods": 2 },
        { "name": "Boxophobic.StyledGUI.StyledMask", "coverage": 0, "coveredlines": 0, "coverablelines": 20, "totallines": 34, "branchcoverage": null, "coveredbranches": 0, "totalbranches": 0, "methodcoverage": 0, "coveredmethods": 0, "totalmethods": 2 },
        { "name": "Boxophobic.StyledGUI.StyledMessage", "coverage": 0, "coveredlines": 0, "coverablelines": 14, "totallines": 31, "branchcoverage": null, "coveredbranches": 0, "totalbranches": 0, "methodcoverage": 0, "coveredmethods": 0, "totalmethods": 2 },
        { "name": "Boxophobic.StyledGUI.StyledRangeOptions", "coverage": 0, "coveredlines": 0, "coverablelines": 7, "totallines": 24, "branchcoverage": null, "coveredbranches": 0, "totalbranches": 0, "methodcoverage": 0, "coveredmethods": 0, "totalmethods": 1 },
        { "name": "Boxophobic.StyledGUI.StyledSpace", "coverage": 0, "coveredlines": 0, "coverablelines": 4, "totallines": 15, "branchcoverage": null, "coveredbranches": 0, "totalbranches": 0, "methodcoverage": 0, "coveredmethods": 0, "totalmethods": 1 },
        { "name": "Boxophobic.StyledGUI.StyledText", "coverage": 0, "coveredlines": 0, "coverablelines": 17, "totallines": 32, "branchcoverage": null, "coveredbranches": 0, "totalbranches": 0, "methodcoverage": 0, "coveredmethods": 0, "totalmethods": 3 },
        { "name": "Boxophobic.StyledGUI.StyledTexturePreview", "coverage": 0, "coveredlines": 0, "coverablelines": 9, "totallines": 20, "branchcoverage": null, "coveredbranches": 0, "totalbranches": 0, "methodcoverage": 0, "coveredmethods": 0, "totalmethods": 2 },
        { "name": "Boxophobic.Utils.SettingsData", "coverage": 0, "coveredlines": 0, "coverablelines": 1, "totallines": 13, "branchcoverage": null, "coveredbranches": 0, "totalbranches": 0, "methodcoverage": 0, "coveredmethods": 0, "totalmethods": 1 },
        { "name": "StyledLabelGizmo", "coverage": 0, "coveredlines": 0, "coverablelines": 2, "totallines": 118, "branchcoverage": null, "coveredbranches": 0, "totalbranches": 0, "methodcoverage": 0, "coveredmethods": 0, "totalmethods": 1 } ] },
      { "name": "EditMode", "classes": 1, "coverage": 0, "coveredlines": 0, "coverablelines": 33, "totallines": 61, "branchcoverage": null, "coveredbranches": 0, "totalbranches": 0, "methodcoverage": 0, "coveredmethods": 0, "totalmethods": 3, "classesinassembly": [
        { "name": "EditModeExtended", "coverage": 0, "coveredlines": 0, "coverablelines": 33, "totallines": 61, "branchcoverage": null, "coveredbranches": 0, "totalbranches": 0, "methodcoverage": 0, "coveredmethods": 0, "totalmethods": 3 } ] },
      { "name": "GameScripts", "classes": 29, "coverage": 69.6, "coveredlines": 803, "coverablelines": 1153, "totallines": 2598, "branchcoverage": null, "coveredbranches": 0, "totalbranches": 0, "methodcoverage": 72.7, "coveredmethods": 104, "totalmethods": 143, "classesinassembly": [
        { "name": "AudioManager", "coverage": 100, "coveredlines": 32, "coverablelines": 32, "totallines": 60, "branchcoverage": null, "coveredbranches": 0, "totalbranches": 0, "methodcoverage": 100, "coveredmethods": 7, "totalmethods": 7 },
        { "name": "CharacterBox", "coverage": 0, "coveredlines": 0, "coverablelines": 4, "totallines": 18, "branchcoverage": null, "coveredbranches": 0, "totalbranches": 0, "methodcoverage": 0, "coveredmethods": 0, "totalmethods": 2 },
        { "name": "Coin", "coverage": 40, "coveredlines": 4, "coverablelines": 10, "totallines": 20, "branchcoverage": null, "coveredbranches": 0, "totalbranches": 0, "methodcoverage": 100, "coveredmethods": 1, "totalmethods": 1 },
        { "name": "CoinGenerator", "coverage": 100, "coveredlines": 13, "coverablelines": 13, "totallines": 31, "branchcoverage": null, "coveredbranches": 0, "totalbranches": 0, "methodcoverage": 100, "coveredmethods": 1, "totalmethods": 1 },
        { "name": "DigitalRuby.RainMaker.BaseRainScript", "coverage": 69, "coveredlines": 134, "coverablelines": 194, "totallines": 362, "branchcoverage": null, "coveredbranches": 0, "totalbranches": 0, "methodcoverage": 62.5, "coveredmethods": 5, "totalmethods": 8 },
        { "name": "DigitalRuby.RainMaker.LoopingAudioSource", "coverage": 81.8, "coveredlines": 27, "coverablelines": 33, "totallines": 362, "branchcoverage": null, "coveredbranches": 0, "totalbranches": 0, "methodcoverage": 100, "coveredmethods": 8, "totalmethods": 8 },
        { "name": "DigitalRuby.RainMaker.RainScript2D", "coverage": 84.5, "coveredlines": 126, "coverablelines": 149, "totallines": 222, "branchcoverage": null, "coveredbranches": 0, "totalbranches": 0, "methodcoverage": 100, "coveredmethods": 10, "totalmethods": 10 },
        { "name": "Enemy", "coverage": 39.6, "coveredlines": 40, "coverablelines": 101, "totallines": 199, "branchcoverage": null, "coveredbranches": 0, "totalbranches": 0, "methodcoverage": 53.8, "coveredmethods": 7, "totalmethods": 13 },
        { "name": "EnemyCreator", "coverage": 30, "coveredlines": 3, "coverablelines": 10, "totallines": 24, "branchcoverage": null, "coveredbranches": 0, "totalbranches": 0, "methodcoverage": 100, "coveredmethods": 1, "totalmethods": 1 },
        { "name": "GameManager", "coverage": 87.2, "coveredlines": 41, "coverablelines": 47, "totallines": 104, "branchcoverage": null, "coveredbranches": 0, "totalbranches": 0, "methodcoverage": 90, "coveredmethods": 9, "totalmethods": 10 },
        { "name": "LedgeDetection", "coverage": 80, "coveredlines": 20, "coverablelines": 25, "totallines": 53, "branchcoverage": null, "coveredbranches": 0, "totalbranches": 0, "methodcoverage": 83.3, "coveredmethods": 5, "totalmethods": 6 },
        { "name": "LevelGenerator", "coverage": 95.2, "coveredlines": 20, "coverablelines": 21, "totallines": 47, "branchcoverage": null, "coveredbranches": 0, "totalbranches": 0, "methodcoverage": 100, "coveredmethods": 3, "totalmethods": 3 },
        { "name": "LimiterGizmos", "coverage": 0, "coveredlines": 0, "coverablelines": 9, "totallines": 24, "branchcoverage": null, "coveredbranches": 0, "totalbranches": 0, "methodcoverage": 0, "coveredmethods": 0, "totalmethods": 1 },
        { "name": "MovingTrap", "coverage": 84.2, "coveredlines": 16, "coverablelines": 19, "totallines": 43, "branchcoverage": null, "coveredbranches": 0, "totalbranches": 0, "methodcoverage": 66.6, "coveredmethods": 2, "totalmethods": 3 },
        { "name": "ParallaxBackground", "coverage": 78.5, "coveredlines": 11, "coverablelines": 14, "totallines": 37, "branchcoverage": null, "coveredbranches": 0, "totalbranches": 0, "methodcoverage": 100, "coveredmethods": 2, "totalmethods": 2 },
        { "name": "PlatformController", "coverage": 100, "coveredlines": 16, "coverablelines": 16, "totallines": 30, "branchcoverage": null, "coveredbranches": 0, "totalbranches": 0, "methodcoverage": 100, "coveredmethods": 2, "totalmethods": 2 },
        { "name": "Player", "coverage": 69.1, "coveredlines": 141, "coverablelines": 204, "totallines": 394, "branchcoverage": null, "coveredbranches": 0, "totalbranches": 0, "methodcoverage": 75, "coveredmethods": 18, "totalmethods": 24 },
        { "name": "PlayFabManager", "coverage": 0, "coveredlines": 0, "coverablelines": 40, "totallines": 105, "branchcoverage": null, "coveredbranches": 0, "totalbranches": 0, "methodcoverage": 0, "coveredmethods": 0, "totalmethods": 10 },
        { "name": "RainController", "coverage": 93.4, "coveredlines": 43, "coverablelines": 46, "totallines": 79, "branchcoverage": null, "coveredbranches": 0, "totalbranches": 0, "methodcoverage": 100, "coveredmethods": 5, "totalmethods": 5 },
        { "name": "SceneController", "coverage": 0, "coveredlines": 0, "coverablelines": 3, "totallines": 12, "branchcoverage": null, "coveredbranches": 0, "totalbranches": 0, "methodcoverage": 0, "coveredmethods": 0, "totalmethods": 1 },
        { "name": "Trap", "coverage": 100, "coveredlines": 10, "coverablelines": 10, "totallines": 24, "branchcoverage": null, "coveredbranches": 0, "totalbranches": 0, "methodcoverage": 100, "coveredmethods": 3, "totalmethods": 3 },
        { "name": "Trigger_DeadZone", "coverage": 0, "coveredlines": 0, "coverablelines": 4, "totallines": 12, "branchcoverage": null, "coveredbranches": 0, "totalbranches": 0, "methodcoverage": 0, "coveredmethods": 0, "totalmethods": 1 },
        { "name": "UI_ButtonJump", "coverage": 0, "coveredlines": 0, "coverablelines": 1, "totallines": 7, "branchcoverage": null, "coveredbranches": 0, "totalbranches": 0, "methodcoverage": 0, "coveredmethods": 0, "totalmethods": 1 },
        { "name": "UI_ButtonSlide", "coverage": 0, "coveredlines": 0, "coverablelines": 1, "totallines": 8, "branchcoverage": null, "coveredbranches": 0, "totalbranches": 0, "methodcoverage": 0, "coveredmethods": 0, "totalmethods": 1 },
        { "name": "UI_EndGame", "coverage": 90, "coveredlines": 9, "coverablelines": 10, "totallines": 28, "branchcoverage": null, "coveredbranches": 0, "totalbranches": 0, "methodcoverage": 100, "coveredmethods": 1, "totalmethods": 1 },
        { "name": "UI_InGame", "coverage": 100, "coveredlines": 15, "coverablelines": 15, "totallines": 44, "branchcoverage": null, "coveredbranches": 0, "totalbranches": 0, "methodcoverage": 100, "coveredmethods": 2, "totalmethods": 2 },
        { "name": "UI_Main", "coverage": 74.5, "coveredlines": 41, "coverablelines": 55, "totallines": 100, "branchcoverage": null, "coveredbranches": 0, "totalbranches": 0, "methodcoverage": 75, "coveredmethods": 6, "totalmethods": 8 },
        { "name": "UI_Shop", "coverage": 63.6, "coveredlines": 35, "coverablelines": 55, "totallines": 119, "branchcoverage": null, "coveredbranches": 0, "totalbranches": 0, "methodcoverage": 100, "coveredmethods": 4, "totalmethods": 4 },
        { "name": "UI_VolumeSlider", "coverage": 50, "coveredlines": 6, "coverablelines": 12, "totallines": 30, "branchcoverage": null, "coveredbranches": 0, "totalbranches": 0, "methodcoverage": 50, "coveredmethods": 2, "totalmethods": 4 } ] },
      { "name": "PlayFab", "classes": 62, "coverage": 0, "coveredlines": 0, "coverablelines": 10281, "totallines": 37157, "branchcoverage": null, "coveredbranches": 0, "totalbranches": 0, "methodcoverage": 0, "coveredmethods": 0, "totalmethods": 1353, "classesinassembly": [
        { "name": "GzipDownloadHandler", "coverage": 0, "coveredlines": 0, "coverablelines": 33, "totallines": 57, "branchcoverage": null, "coveredbranches": 0, "totalbranches": 0, "methodcoverage": 0, "coveredmethods": 0, "totalmethods": 5 },
        { "name": "PlayFab.Events.PlayFabEvents", "coverage": 0, "coveredlines": 0, "coverablelines": 1793, "totallines": 3727, "branchcoverage": null, "coveredbranches": 0, "totalbranches": 0, "methodcoverage": 0, "coveredmethods": 0, "totalmethods": 5 },
        { "name": "PlayFab.Internal.ApiProcessingEventArgs", "coverage": 0, "coveredlines": 0, "coverablelines": 3, "totallines": 504, "branchcoverage": null, "coveredbranches": 0, "totalbranches": 0, "methodcoverage": 0, "coveredmethods": 0, "totalmethods": 1 },
        { "name": "PlayFab.Internal.CallRequestContainer", "coverage": 0, "coveredlines": 0, "coverablelines": 11, "totallines": 61, "branchcoverage": null, "coveredbranches": 0, "totalbranches": 0, "methodcoverage": 0, "coveredmethods": 0, "totalmethods": 1 },
        { "name": "PlayFab.Internal.Log", "coverage": 0, "coveredlines": 0, "coverablelines": 24, "totallines": 44, "branchcoverage": null, "coveredbranches": 0, "totalbranches": 0, "methodcoverage": 0, "coveredmethods": 0, "totalmethods": 4 },
        { "name": "PlayFab.Internal.PlayFabDeviceUtil", "coverage": 0, "coveredlines": 0, "coverablelines": 60, "totallines": 109, "branchcoverage": null, "coveredbranches": 0, "totalbranches": 0, "methodcoverage": 0, "coveredmethods": 0, "totalmethods": 4 },
        { "name": "PlayFab.Internal.PlayFabHttp", "coverage": 0, "coveredlines": 0, "coverablelines": 233, "totallines": 504, "branchcoverage": null, "coveredbranches": 0, "totalbranches": 0, "methodcoverage": 0, "coveredmethods": 0, "totalmethods": 26 },
        { "name": "PlayFab.Internal.PlayFabUnityHttp", "coverage": 0, "coveredlines": 0, "coverablelines": 161, "totallines": 280, "branchcoverage": null, "coveredbranches": 0, "totalbranches": 0, "methodcoverage": 0, "coveredmethods": 0, "totalmethods": 14 },
        { "name": "PlayFab.Internal.PlayFabUtil", "coverage": 0, "coveredlines": 0, "coverablelines": 71, "totallines": 157, "branchcoverage": null, "coveredbranches": 0, "totalbranches": 0, "methodcoverage": 0, "coveredmethods": 0, "totalmethods": 7 },
        { "name": "PlayFab.Internal.PlayFabWebRequest", "coverage": 0, "coveredlines": 0, "coverablelines": 356, "totallines": 544, "branchcoverage": null, "coveredbranches": 0, "totalbranches": 0, "methodcoverage": 0, "coveredmethods": 0, "totalmethods": 23 },
        { "name": "PlayFab.Internal.SingletonMonoBehaviour[T]", "coverage": 0, "coveredlines": 0, "coverablelines": 31, "totallines": 58, "branchcoverage": null, "coveredbranches": 0, "totalbranches": 0, "methodcoverage": 0, "coveredmethods": 0, "totalmethods": 4 },
        { "name": "PlayFab.Json.JsonArray", "coverage": 0, "coveredlines": 0, "coverablelines": 5, "totallines": 2081, "branchcoverage": null, "coveredbranches": 0, "totalbranches": 0, "methodcoverage": 0, "coveredmethods": 0, "totalmethods": 3 },
        { "name": "PlayFab.Json.JsonObject", "coverage": 0, "coveredlines": 0, "coverablelines": 68, "totallines": 2081, "branchcoverage": null, "coveredbranches": 0, "totalbranches": 0, "methodcoverage": 0, "coveredmethods": 0, "totalmethods": 22 },
        { "name": "PlayFab.Json.JsonProperty", "coverage": 0, "coveredlines": 0, "coverablelines": 2, "totallines": 2081, "branchcoverage": null, "coveredbranches": 0, "totalbranches": 0, "methodcoverage": 0, "coveredmethods": 0, "totalmethods": 1 },
        { "name": "PlayFab.Json.PlayFabSimpleJson", "coverage": 0, "coveredlines": 0, "coverablelines": 487, "totallines": 2081, "branchcoverage": null, "coveredbranches": 0, "totalbranches": 0, "methodcoverage": 0, "coveredmethods": 0, "totalmethods": 26 },
        { "name": "PlayFab.Json.PocoJsonSerializerStrategy", "coverage": 0, "coveredlines": 0, "coverablelines": 234, "totallines": 2081, "branchcoverage": null, "coveredbranches": 0, "totalbranches": 0, "methodcoverage": 0, "coveredmethods": 0, "totalmethods": 12 },
        { "name": "PlayFab.Json.ReflectionUtils", "coverage": 0, "coveredlines": 0, "coverablelines": 143, "totallines": 2081, "branchcoverage": null, "coveredbranches": 0, "totalbranches": 0, "methodcoverage": 0, "coveredmethods": 0, "totalmethods": 31 },
        { "name": "PlayFab.Json.ReflectionUtilsThreadSafeDictionary[TKey,TValue]", "coverage": 0, "coveredlines": 0, "coverablelines": 64, "totallines": 2081, "branchcoverage": null, "coveredbranches": 0, "totalbranches": 0, "methodcoverage": 0, "coveredmethods": 0, "totalmethods": 20 },
        { "name": "PlayFab.Json.SimpleJsonInstance", "coverage": 0, "coveredlines": 0, "coverablelines": 63, "totallines": 108, "branchcoverage": null, "coveredbranches": 0, "totalbranches": 0, "methodcoverage": 0, "coveredmethods": 0, "totalmethods": 8 },
        { "name": "PlayFab.PlayFabAddonAPI", "coverage": 0, "coveredlines": 0, "coverablelines": 187, "totallines": 429, "branchcoverage": null, "coveredbranches": 0, "totalbranches": 0, "methodcoverage": 0, "coveredmethods": 0, "totalmethods": 33 },
        { "name": "PlayFab.PlayFabAddonInstanceAPI", "coverage": 0, "coveredlines": 0, "coverablelines": 204, "totallines": 387, "branchcoverage": null, "coveredbranches": 0, "totalbranches": 0, "methodcoverage": 0, "coveredmethods": 0, "totalmethods": 34 },
        { "name": "PlayFab.PlayFabApiSettings", "coverage": 0, "coveredlines": 0, "coverablelines": 14, "totallines": 102, "branchcoverage": null, "coveredbranches": 0, "totalbranches": 0, "methodcoverage": 0, "coveredmethods": 0, "totalmethods": 19 },
        { "name": "PlayFab.PlayFabAuthenticationAPI", "coverage": 0, "coveredlines": 0, "coverablelines": 33, "totallines": 104, "branchcoverage": null, "coveredbranches": 0, "totalbranches": 0, "methodcoverage": 0, "coveredmethods": 0, "totalmethods": 7 },
        { "name": "PlayFab.PlayFabAuthenticationContext", "coverage": 0, "coveredlines": 0, "coverablelines": 37, "totallines": 87, "branchcoverage": null, "coveredbranches": 0, "totalbranches": 0, "methodcoverage": 0, "coveredmethods": 0, "totalmethods": 7 },
        { "name": "PlayFab.PlayFabAuthenticationInstanceAPI", "coverage": 0, "coveredlines": 0, "coverablelines": 55, "totallines": 121, "branchcoverage": null, "coveredbranches": 0, "totalbranches": 0, "methodcoverage": 0, "coveredmethods": 0, "totalmethods": 10 },
        { "name": "PlayFab.PlayFabClientAPI", "coverage": 0, "coveredlines": 0, "coverablelines": 1050, "totallines": 2429, "branchcoverage": null, "coveredbranches": 0, "totalbranches": 0, "methodcoverage": 0, "coveredmethods": 0, "totalmethods": 177 },
        { "name": "PlayFab.PlayFabClientInstanceAPI", "coverage": 0, "coveredlines": 0, "coverablelines": 1072, "totallines": 2108, "branchcoverage": null, "coveredbranches": 0, "totalbranches": 0, "methodcoverage": 0, "coveredmethods": 0, "totalmethods": 180 },
        { "name": "PlayFab.PlayFabCloudScriptAPI", "coverage": 0, "coveredlines": 0, "coverablelines": 104, "totallines": 244, "branchcoverage": null, "coveredbranches": 0, "totalbranches": 0, "methodcoverage": 0, "coveredmethods": 0, "totalmethods": 18 },
        { "name": "PlayFab.PlayFabCloudScriptInstanceAPI", "coverage": 0, "coveredlines": 0, "coverablelines": 114, "totallines": 224, "branchcoverage": null, "coveredbranches": 0, "totalbranches": 0, "methodcoverage": 0, "coveredmethods": 0, "totalmethods": 19 },
        { "name": "PlayFab.PlayFabDataAPI", "coverage": 0, "coveredlines": 0, "coverablelines": 49, "totallines": 133, "branchcoverage": null, "coveredbranches": 0, "totalbranches": 0, "methodcoverage": 0, "coveredmethods": 0, "totalmethods": 10 },
        { "name": "PlayFab.PlayFabDataGatherer", "coverage": 0, "coveredlines": 0, "coverablelines": 39, "totallines": 138, "branchcoverage": null, "coveredbranches": 0, "totalbranches": 0, "methodcoverage": 0, "coveredmethods": 0, "totalmethods": 2 },
        { "name": "PlayFab.PlayFabDataInstanceAPI", "coverage": 0, "coveredlines": 0, "coverablelines": 66, "totallines": 137, "branchcoverage": null, "coveredbranches": 0, "totalbranches": 0, "methodcoverage": 0, "coveredmethods": 0, "totalmethods": 11 },
        { "name": "PlayFab.PlayFabEconomyAPI", "coverage": 0, "coveredlines": 0, "coverablelines": 283, "totallines": 688, "branchcoverage": null, "coveredbranches": 0, "totalbranches": 0, "methodcoverage": 0, "coveredmethods": 0, "totalmethods": 49 },
        { "name": "PlayFab.PlayFabEconomyInstanceAPI", "coverage": 0, "coveredlines": 0, "coverablelines": 300, "totallines": 614, "branchcoverage": null, "coveredbranches": 0, "totalbranches": 0, "methodcoverage": 0, "coveredmethods": 0, "totalmethods": 50 },
        { "name": "PlayFab.PlayFabError", "coverage": 0, "coveredlines": 0, "coverablelines": 21, "totallines": 1003, "branchcoverage": null, "coveredbranches": 0, "totalbranches": 0, "methodcoverage": 0, "coveredmethods": 0, "totalmethods": 3 },
        { "name": "PlayFab.PlayFabEventsAPI", "coverage": 0, "coveredlines": 0, "coverablelines": 85, "totallines": 209, "branchcoverage": null, "coveredbranches": 0, "totalbranches": 0, "methodcoverage": 0, "coveredmethods": 0, "totalmethods": 16 },
        { "name": "PlayFab.PlayFabEventsInstanceAPI", "coverage": 0, "coveredlines": 0, "coverablelines": 102, "totallines": 203, "branchcoverage": null, "coveredbranches": 0, "totalbranches": 0, "methodcoverage": 0, "coveredmethods": 0, "totalmethods": 17 },
        { "name": "PlayFab.PlayFabException", "coverage": 0, "coveredlines": 0, "coverablelines": 4, "totallines": 1003, "branchcoverage": null, "coveredbranches": 0, "totalbranches": 0, "methodcoverage": 0, "coveredmethods": 0, "totalmethods": 1 },
        { "name": "PlayFab.PlayFabExperimentationAPI", "coverage": 0, "coveredlines": 0, "coverablelines": 85, "totallines": 208, "branchcoverage": null, "coveredbranches": 0, "totalbranches": 0, "methodcoverage": 0, "coveredmethods": 0, "totalmethods": 16 },
        { "name": "PlayFab.PlayFabExperimentationInstanceAPI", "coverage": 0, "coveredlines": 0, "coverablelines": 102, "totallines": 200, "branchcoverage": null, "coveredbranches": 0, "totalbranches": 0, "methodcoverage": 0, "coveredmethods": 0, "totalmethods": 17 },
        { "name": "PlayFab.PlayFabGroupsAPI", "coverage": 0, "coveredlines": 0, "coverablelines": 157, "totallines": 366, "branchcoverage": null, "coveredbranches": 0, "totalbranches": 0, "methodcoverage": 0, "coveredmethods": 0, "totalmethods": 28 },
        { "name": "PlayFab.PlayFabGroupsInstanceAPI", "coverage": 0, "coveredlines": 0, "coverablelines": 174, "totallines": 334, "branchcoverage": null, "coveredbranches": 0, "totalbranches": 0, "methodcoverage": 0, "coveredmethods": 0, "totalmethods": 29 },
        { "name": "PlayFab.PlayFabInsightsAPI", "coverage": 0, "coveredlines": 0, "coverablelines": 43, "totallines": 119, "branchcoverage": null, "coveredbranches": 0, "totalbranches": 0, "methodcoverage": 0, "coveredmethods": 0, "totalmethods": 9 },
        { "name": "PlayFab.PlayFabInsightsInstanceAPI", "coverage": 0, "coveredlines": 0, "coverablelines": 60, "totallines": 125, "branchcoverage": null, "coveredbranches": 0, "totalbranches": 0, "methodcoverage": 0, "coveredmethods": 0, "totalmethods": 10 },
        { "name": "PlayFab.PlayFabLocalizationAPI", "coverage": 0, "coveredlines": 0, "coverablelines": 13, "totallines": 52, "branchcoverage": null, "coveredbranches": 0, "totalbranches": 0, "methodcoverage": 0, "coveredmethods": 0, "totalmethods": 4 },
        { "name": "PlayFab.PlayFabLocalizationInstanceAPI", "coverage": 0, "coveredlines": 0, "coverablelines": 30, "totallines": 68, "branchcoverage": null, "coveredbranches": 0, "totalbranches": 0, "methodcoverage": 0, "coveredmethods": 0, "totalmethods": 5 },
        { "name": "PlayFab.PlayFabMultiplayerAPI", "coverage": 0, "coveredlines": 0, "coverablelines": 528, "totallines": 1183, "branchcoverage": null, "coveredbranches": 0, "totalbranches": 0, "methodcoverage": 0, "coveredmethods": 0, "totalmethods": 90 },
        { "name": "PlayFab.PlayFabMultiplayerInstanceAPI", "coverage": 0, "coveredlines": 0, "coverablelines": 545, "totallines": 1027, "branchcoverage": null, "coveredbranches": 0, "totalbranches": 0, "methodcoverage": 0, "coveredmethods": 0, "totalmethods": 91 },
        { "name": "PlayFab.PlayFabProfilesAPI", "coverage": 0, "coveredlines": 0, "coverablelines": 61, "totallines": 158, "branchcoverage": null, "coveredbranches": 0, "totalbranches": 0, "methodcoverage": 0, "coveredmethods": 0, "totalmethods": 12 },
        { "name": "PlayFab.PlayFabProfilesInstanceAPI", "coverage": 0, "coveredlines": 0, "coverablelines": 78, "totallines": 158, "branchcoverage": null, "coveredbranches": 0, "totalbranches": 0, "methodcoverage": 0, "coveredmethods": 0, "totalmethods": 13 },
        { "name": "PlayFab.PlayFabProgressionAPI", "coverage": 0, "coveredlines": 0, "coverablelines": 145, "totallines": 339, "branchcoverage": null, "coveredbranches": 0, "totalbranches": 0, "methodcoverage": 0, "coveredmethods": 0, "totalmethods": 26 },
        { "name": "PlayFab.PlayFabProgressionInstanceAPI", "coverage": 0, "coveredlines": 0, "coverablelines": 162, "totallines": 311, "branchcoverage": null, "coveredbranches": 0, "totalbranches": 0, "methodcoverage": 0, "coveredmethods": 0, "totalmethods": 27 },
        { "name": "PlayFab.PlayFabSettings", "coverage": 0, "coveredlines": 0, "coverablelines": 120, "totallines": 250, "branchcoverage": null, "coveredbranches": 0, "totalbranches": 0, "methodcoverage": 0, "coveredmethods": 0, "totalmethods": 34 },
        { "name": "PlayFab.PlayFabSettingsRedirect", "coverage": 0, "coveredlines": 0, "coverablelines": 17, "totallines": 102, "branchcoverage": null, "coveredbranches": 0, "totalbranches": 0, "methodcoverage": 0, "coveredmethods": 0, "totalmethods": 17 },
        { "name": "PlayFab.PluginContractKeyComparator", "coverage": 0, "coveredlines": 0, "coverablelines": 6, "totallines": 23, "branchcoverage": null, "coveredbranches": 0, "totalbranches": 0, "methodcoverage": 0, "coveredmethods": 0, "totalmethods": 2 },
        { "name": "PlayFab.PluginManager", "coverage": 0, "coveredlines": 0, "coverablelines": 43, "totallines": 110, "branchcoverage": null, "coveredbranches": 0, "totalbranches": 0, "methodcoverage": 0, "coveredmethods": 0, "totalmethods": 8 },
        { "name": "PlayFab.Public.PlayFabLogger", "coverage": 0, "coveredlines": 0, "coverablelines": 6, "totallines": 270, "branchcoverage": null, "coveredbranches": 0, "totalbranches": 0, "methodcoverage": 0, "coveredmethods": 0, "totalmethods": 3 },
        { "name": "PlayFab.Public.PlayFabLoggerBase", "coverage": 0, "coveredlines": 0, "coverablelines": 111, "totallines": 270, "branchcoverage": null, "coveredbranches": 0, "totalbranches": 0, "methodcoverage": 0, "coveredmethods": 0, "totalmethods": 15 },
        { "name": "PlayFab.Public.ScreenTimeTracker", "coverage": 0, "coveredlines": 0, "coverablelines": 106, "totallines": 255, "branchcoverage": null, "coveredbranches": 0, "totalbranches": 0, "methodcoverage": 0, "coveredmethods": 0, "totalmethods": 11 },
        { "name": "PlayFab.SharedModels.PlayFabBaseModel", "coverage": 0, "coveredlines": 0, "coverablelines": 4, "totallines": 44, "branchcoverage": null, "coveredbranches": 0, "totalbranches": 0, "methodcoverage": 0, "coveredmethods": 0, "totalmethods": 1 },
        { "name": "PlayFab.WsaReflectionExtensions", "coverage": 0, "coveredlines": 0, "coverablelines": 12, "totallines": 66, "branchcoverage": null, "coveredbranches": 0, "totalbranches": 0, "methodcoverage": 0, "coveredmethods": 0, "totalmethods": 4 },
        { "name": "PlayFabSharedSettings", "coverage": 0, "coveredlines": 0, "coverablelines": 12, "totallines": 36, "branchcoverage": null, "coveredbranches": 0, "totalbranches": 0, "methodcoverage": 0, "coveredmethods": 0, "totalmethods": 1 } ] },
      { "name": "PlayFabEditorExtensions", "classes": 29, "coverage": 0, "coveredlines": 0, "coverablelines": 2824, "totallines": 16330, "branchcoverage": null, "coveredbranches": 0, "totalbranches": 0, "methodcoverage": 0, "coveredmethods": 0, "totalmethods": 267, "classesinassembly": [
        { "name": "PlayFab.PfEditor.EditorCoroutine", "coverage": 0, "coveredlines": 0, "coverablelines": 83, "totallines": 145, "branchcoverage": null, "coveredbranches": 0, "totalbranches": 0, "methodcoverage": 0, "coveredmethods": 0, "totalmethods": 7 },
        { "name": "PlayFab.PfEditor.EditorModels.PlayFabError", "coverage": 0, "coveredlines": 0, "coverablelines": 12, "totallines": 264, "branchcoverage": null, "coveredbranches": 0, "totalbranches": 0, "methodcoverage": 0, "coveredmethods": 0, "totalmethods": 2 },
        { "name": "PlayFab.PfEditor.FixedWidthLabel", "coverage": 0, "coveredlines": 0, "coverablelines": 15, "totallines": 149, "branchcoverage": null, "coveredbranches": 0, "totalbranches": 0, "methodcoverage": 0, "coveredmethods": 0, "totalmethods": 3 },
        { "name": "PlayFab.PfEditor.Json.JsonArray", "coverage": 0, "coveredlines": 0, "coverablelines": 5, "totallines": 2047, "branchcoverage": null, "coveredbranches": 0, "totalbranches": 0, "methodcoverage": 0, "coveredmethods": 0, "totalmethods": 3 },
        { "name": "PlayFab.PfEditor.Json.JsonObject", "coverage": 0, "coveredlines": 0, "coverablelines": 68, "totallines": 2047, "branchcoverage": null, "coveredbranches": 0, "totalbranches": 0, "methodcoverage": 0, "coveredmethods": 0, "totalmethods": 22 },
        { "name": "PlayFab.PfEditor.Json.JsonWrapper", "coverage": 0, "coveredlines": 0, "coverablelines": 18, "totallines": 80, "branchcoverage": null, "coveredbranches": 0, "totalbranches": 0, "methodcoverage": 0, "coveredmethods": 0, "totalmethods": 8 },
        { "name": "PlayFab.PfEditor.Json.PlayFabSimpleJson", "coverage": 0, "coveredlines": 0, "coverablelines": 492, "totallines": 2047, "branchcoverage": null, "coveredbranches": 0, "totalbranches": 0, "methodcoverage": 0, "coveredmethods": 0, "totalmethods": 28 },
        { "name": "PlayFab.PfEditor.Json.PocoJsonSerializerStrategy", "coverage": 0, "coveredlines": 0, "coverablelines": 209, "totallines": 2047, "branchcoverage": null, "coveredbranches": 0, "totalbranches": 0, "methodcoverage": 0, "coveredmethods": 0, "totalmethods": 11 },
        { "name": "PlayFab.PfEditor.Json.ReflectionUtils", "coverage": 0, "coveredlines": 0, "coverablelines": 141, "totallines": 2047, "branchcoverage": null, "coveredbranches": 0, "totalbranches": 0, "methodcoverage": 0, "coveredmethods": 0, "totalmethods": 31 },
        { "name": "PlayFab.PfEditor.Json.ReflectionUtilsThreadSafeDictionary[TKey,TValue]", "coverage": 0, "coveredlines": 0, "coverablelines": 64, "totallines": 2047, "branchcoverage": null, "coveredbranches": 0, "totalbranches": 0, "methodcoverage": 0, "coveredmethods": 0, "totalmethods": 20 },
        { "name": "PlayFab.PfEditor.Json.SimpleJsonInstance", "coverage": 0, "coveredlines": 0, "coverablelines": 15, "totallines": 80, "branchcoverage": null, "coveredbranches": 0, "totalbranches": 0, "methodcoverage": 0, "coveredmethods": 0, "totalmethods": 5 },
        { "name": "PlayFab.PfEditor.PlayFabEditor", "coverage": 0, "coveredlines": 0, "coverablelines": 278, "totallines": 432, "branchcoverage": null, "coveredbranches": 0, "totalbranches": 0, "methodcoverage": 0, "coveredmethods": 0, "totalmethods": 24 },
        { "name": "PlayFab.PfEditor.PlayFabEditorDataService", "coverage": 0, "coveredlines": 0, "coverablelines": 62, "totallines": 105, "branchcoverage": null, "coveredbranches": 0, "totalbranches": 0, "methodcoverage": 0, "coveredmethods": 0, "totalmethods": 15 },
        { "name": "PlayFab.PfEditor.PlayFabEditorHeader", "coverage": 0, "coveredlines": 0, "coverablelines": 28, "totallines": 52, "branchcoverage": null, "coveredbranches": 0, "totalbranches": 0, "methodcoverage": 0, "coveredmethods": 0, "totalmethods": 1 },
        { "name": "PlayFab.PfEditor.PlayFabEditorHelper", "coverage": 0, "coveredlines": 0, "coverablelines": 117, "totallines": 229, "branchcoverage": null, "coveredbranches": 0, "totalbranches": 0, "methodcoverage": 0, "coveredmethods": 0, "totalmethods": 8 },
        { "name": "PlayFab.PfEditor.PlayFabEditorHelpMenu", "coverage": 0, "coveredlines": 0, "coverablelines": 175, "totallines": 235, "branchcoverage": null, "coveredbranches": 0, "totalbranches": 0, "methodcoverage": 0, "coveredmethods": 0, "totalmethods": 5 },
        { "name": "PlayFab.PfEditor.PlayFabEditorHttp", "coverage": 0, "coveredlines": 0, "coverablelines": 71, "totallines": 148, "branchcoverage": null, "coveredbranches": 0, "totalbranches": 0, "methodcoverage": 0, "coveredmethods": 0, "totalmethods": 6 },
        { "name": "PlayFab.PfEditor.PlayFabEditorMenu", "coverage": 0, "coveredlines": 0, "coverablelines": 126, "totallines": 174, "branchcoverage": null, "coveredbranches": 0, "totalbranches": 0, "methodcoverage": 0, "coveredmethods": 0, "totalmethods": 8 },
        { "name": "PlayFab.PfEditor.PlayFabEditorPrefsSO", "coverage": 0, "coveredlines": 0, "coverablelines": 25, "totallines": 66, "branchcoverage": null, "coveredbranches": 0, "totalbranches": 0, "methodcoverage": 0, "coveredmethods": 0, "totalmethods": 8 },
        { "name": "PlayFab.PfEditor.PlayFabEditorSDKTools", "coverage": 0, "coveredlines": 0, "coverablelines": 391, "totallines": 544, "branchcoverage": null, "coveredbranches": 0, "totalbranches": 0, "methodcoverage": 0, "coveredmethods": 0, "totalmethods": 16 },
        { "name": "PlayFab.PfEditor.PlayFabEditorSettings", "coverage": 0, "coveredlines": 0, "coverablelines": 60, "totallines": 116, "branchcoverage": null, "coveredbranches": 0, "totalbranches": 0, "methodcoverage": 0, "coveredmethods": 0, "totalmethods": 6 },
        { "name": "PlayFab.PfEditor.PlayFabEditorUtil", "coverage": 0, "coveredlines": 0, "coverablelines": 46, "totallines": 118, "branchcoverage": null, "coveredbranches": 0, "totalbranches": 0, "methodcoverage": 0, "coveredmethods": 0, "totalmethods": 6 },
        { "name": "PlayFab.PfEditor.PlayFabGuiFieldHelper", "coverage": 0, "coveredlines": 0, "coverablelines": 23, "totallines": 149, "branchcoverage": null, "coveredbranches": 0, "totalbranches": 0, "methodcoverage": 0, "coveredmethods": 0, "totalmethods": 2 },
        { "name": "PlayFab.PfEditor.ProgressBar", "coverage": 0, "coveredlines": 0, "coverablelines": 118, "totallines": 155, "branchcoverage": null, "coveredbranches": 0, "totalbranches": 0, "methodcoverage": 0, "coveredmethods": 0, "totalmethods": 4 },
        { "name": "PlayFab.PfEditor.SubMenuComponent", "coverage": 0, "coveredlines": 0, "coverablelines": 144, "totallines": 211, "branchcoverage": null, "coveredbranches": 0, "totalbranches": 0, "methodcoverage": 0, "coveredmethods": 0, "totalmethods": 8 },
        { "name": "PlayFab.PfEditor.UnityGuiToggler", "coverage": 0, "coveredlines": 0, "coverablelines": 8, "totallines": 149, "branchcoverage": null, "coveredbranches": 0, "totalbranches": 0, "methodcoverage": 0, "coveredmethods": 0, "totalmethods": 2 },
        { "name": "PlayFab.PfEditor.UnityHorizontal", "coverage": 0, "coveredlines": 0, "coverablelines": 11, "totallines": 149, "branchcoverage": null, "coveredbranches": 0, "totalbranches": 0, "methodcoverage": 0, "coveredmethods": 0, "totalmethods": 3 },
        { "name": "PlayFab.PfEditor.UnityVertical", "coverage": 0, "coveredlines": 0, "coverablelines": 11, "totallines": 149, "branchcoverage": null, "coveredbranches": 0, "totalbranches": 0, "methodcoverage": 0, "coveredmethods": 0, "totalmethods": 3 },
        { "name": "PlayFab.PfEditor.ZeroIndent", "coverage": 0, "coveredlines": 0, "coverablelines": 8, "totallines": 149, "branchcoverage": null, "coveredbranches": 0, "totalbranches": 0, "methodcoverage": 0, "coveredmethods": 0, "totalmethods": 2 } ] },
      { "name": "PlayFabSDKEditor", "classes": 2, "coverage": 0, "coveredlines": 0, "coverablelines": 22, "totallines": 59, "branchcoverage": null, "coveredbranches": 0, "totalbranches": 0, "methodcoverage": 0, "coveredmethods": 0, "totalmethods": 6, "classesinassembly": [
        { "name": "MakeScriptableObject", "coverage": 0, "coveredlines": 0, "coverablelines": 7, "totallines": 21, "branchcoverage": null, "coveredbranches": 0, "totalbranches": 0, "methodcoverage": 0, "coveredmethods": 0, "totalmethods": 1 },
        { "name": "PlayFab.PfEditor.PlayFabHelp", "coverage": 0, "coveredlines": 0, "coverablelines": 15, "totallines": 38, "branchcoverage": null, "coveredbranches": 0, "totalbranches": 0, "methodcoverage": 0, "coveredmethods": 0, "totalmethods": 5 } ] },
      { "name": "PlayMode", "classes": 11, "coverage": 36, "coveredlines": 827, "coverablelines": 2294, "totallines": 4306, "branchcoverage": null, "coveredbranches": 0, "totalbranches": 0, "methodcoverage": 32.2, "coveredmethods": 67, "totalmethods": 208, "classesinassembly": [
        { "name": "AdditionalAutoTests", "coverage": 0, "coveredlines": 0, "coverablelines": 367, "totallines": 702, "branchcoverage": null, "coveredbranches": 0, "totalbranches": 0, "methodcoverage": 0, "coveredmethods": 0, "totalmethods": 29 },
        { "name": "AnimationTests", "coverage": 0, "coveredlines": 0, "coverablelines": 78, "totallines": 169, "branchcoverage": null, "coveredbranches": 0, "totalbranches": 0, "methodcoverage": 0, "coveredmethods": 0, "totalmethods": 7 },
        { "name": "CoverageBoostTests", "coverage": 97.6, "coveredlines": 827, "coverablelines": 847, "totallines": 1580, "branchcoverage": null, "coveredbranches": 0, "totalbranches": 0, "methodcoverage": 100, "coveredmethods": 67, "totalmethods": 67 },
        { "name": "GameplayTests", "coverage": 0, "coveredlines": 0, "coverablelines": 289, "totallines": 602, "branchcoverage": null, "coveredbranches": 0, "totalbranches": 0, "methodcoverage": 0, "coveredmethods": 0, "totalmethods": 23 },
        { "name": "HoangTest", "coverage": 0, "coveredlines": 0, "coverablelines": 125, "totallines": 214, "branchcoverage": null, "coveredbranches": 0, "totalbranches": 0, "methodcoverage": 0, "coveredmethods": 0, "totalmethods": 15 },
        { "name": "HungTest", "coverage": 0, "coveredlines": 0, "coverablelines": 129, "totallines": 220, "branchcoverage": null, "coveredbranches": 0, "totalbranches": 0, "methodcoverage": 0, "coveredmethods": 0, "totalmethods": 15 },
        { "name": "HuyTest", "coverage": 0, "coveredlines": 0, "coverablelines": 93, "totallines": 164, "branchcoverage": null, "coveredbranches": 0, "totalbranches": 0, "methodcoverage": 0, "coveredmethods": 0, "totalmethods": 15 },
        { "name": "PhatTest", "coverage": 0, "coveredlines": 0, "coverablelines": 143, "totallines": 234, "branchcoverage": null, "coveredbranches": 0, "totalbranches": 0, "methodcoverage": 0, "coveredmethods": 0, "totalmethods": 15 },
        { "name": "SoundTests", "coverage": 0, "coveredlines": 0, "coverablelines": 65, "totallines": 127, "branchcoverage": null, "coveredbranches": 0, "totalbranches": 0, "methodcoverage": 0, "coveredmethods": 0, "totalmethods": 4 },
        { "name": "UITests", "coverage": 0, "coveredlines": 0, "coverablelines": 45, "totallines": 96, "branchcoverage": null, "coveredbranches": 0, "totalbranches": 0, "methodcoverage": 0, "coveredmethods": 0, "totalmethods": 3 },
        { "name": "VuTest", "coverage": 0, "coveredlines": 0, "coverablelines": 113, "totallines": 198, "branchcoverage": null, "coveredbranches": 0, "totalbranches": 0, "methodcoverage": 0, "coveredmethods": 0, "totalmethods": 15 } ] } ]
  }
}